{
    "twilight sparkle": {
        "harmony": 44,
        "equestria": 90,
        "hmm": 29,
        "elements": 61,
        "heard": 19,
        "oh": 261,
        "sorry": 106,
        "girls": 44,
        "lot": 37,
        "studying": 16,
        "catch": 14,
        "spike": 337,
        "quick": 20,
        "time": 213,
        "sort": 12,
        "grunts": 12,
        "ah": 14,
        "aha": 7,
        "mare": 10,
        "moon": 35,
        "pony": 102,
        "times": 15,
        "powerful": 24,
        "legend": 7,
        "day": 59,
        "stars": 10,
        "escape": 11,
        "bring": 27,
        "gasp": 30,
        "means": 26,
        "please": 58,
        "princess": 233,
        "teacher": 11,
        "studies": 7,
        "magic": 113,
        "led": 6,
        "disaster": 19,
        "uh": 103,
        "ugh": 47,
        "bad": 31,
        "happen": 27,
        "nightmare": 23,
        "night": 39,
        "terrible": 16,
        "true": 24,
        "student": 12,
        "twilight": 38,
        "sparkle": 14,
        "send": 30,
        "course": 54,
        "tomorrow": 19,
        "summer": 6,
        "sun": 18,
        "celebration": 9,
        "told": 24,
        "worried": 11,
        "completely": 6,
        "action": 6,
        "mm": 12,
        "hm": 11,
        "yes": 75,
        "check": 25,
        "fast": 10,
        "library": 18,
        "am": 64,
        "royal": 10,
        "rest": 20,
        "friends": 162,
        "thank": 53,
        "um": 35,
        "hello": 22,
        "sigh": 18,
        "afternoon": 7,
        "name": 15,
        "actually": 47,
        "clears": 12,
        "throat": 12,
        "charge": 6,
        "food": 7,
        "thanks": 38,
        "nervous": 21,
        "laughter": 7,
        "okay": 125,
        "awful": 15,
        "fine": 41,
        "pie": 80,
        "doing": 115,
        "job": 19,
        "guess": 53,
        "rainbow": 135,
        "dash": 102,
        "supposed": 33,
        "keeping": 8,
        "sky": 15,
        "sent": 17,
        "weather": 6,
        "wonderbolts": 14,
        "pegasus": 6,
        "coming": 32,
        "beautiful": 15,
        "mean": 82,
        "mane": 8,
        "story": 13,
        "wait": 68,
        "help": 170,
        "canterlot": 31,
        "focus": 6,
        "list": 13,
        "music": 7,
        "pause": 8,
        "looks": 40,
        "easy": 19,
        "staying": 8,
        "ponyville": 71,
        "baby": 15,
        "dragon": 39,
        "sleep": 14,
        "convince": 6,
        "running": 14,
        "study": 14,
        "crazy": 12,
        "ponies": 98,
        "trying": 39,
        "light": 7,
        "surprised": 10,
        "quiet": 7,
        "town": 10,
        "learn": 35,
        "silly": 9,
        "ridiculous": 8,
        "friend": 75,
        "hope": 37,
        "wanna": 21,
        "stop": 75,
        "read": 31,
        "called": 17,
        "six": 14,
        "five": 16,
        "generosity": 6,
        "complete": 8,
        "mystery": 8,
        "ancient": 12,
        "castle": 34,
        "sisters": 6,
        "look": 94,
        "appreciate": 9,
        "offer": 7,
        "own": 41,
        "none": 13,
        "applejack": 102,
        "phew": 11,
        "gotta": 36,
        "past": 26,
        "pinkie": 204,
        "run": 15,
        "tell": 74,
        "excuse": 11,
        "rarity": 111,
        "tail": 7,
        "cross": 6,
        "whoa": 24,
        "taking": 22,
        "listen": 31,
        "found": 26,
        "careful": 8,
        "book": 69,
        "cause": 6,
        "element": 16,
        "idea": 42,
        "stand": 8,
        "aah": 6,
        "wrong": 46,
        "spirits": 6,
        "doubt": 6,
        "represents": 8,
        "spirit": 9,
        "fluttershy": 116,
        "banished": 6,
        "fear": 9,
        "danger": 6,
        "challenge": 6,
        "moment": 14,
        "realized": 11,
        "happy": 37,
        "hear": 21,
        "inside": 15,
        "heart": 33,
        "gasps": 53,
        "celestia": 118,
        "learned": 37,
        "wonderful": 18,
        "leave": 20,
        "harder": 10,
        "glad": 42,
        "hard": 30,
        "ooh": 25,
        "morning": 20,
        "laughs": 14,
        "nervously": 12,
        "eh": 8,
        "delicious": 6,
        "letter": 23,
        "wow": 40,
        "gala": 10,
        "aw": 7,
        "nice": 23,
        "yeah": 33,
        "decide": 8,
        "whoever": 9,
        "reason": 21,
        "ticket": 9,
        "pretty": 39,
        "chuckles": 8,
        "decisions": 6,
        "straight": 6,
        "eat": 10,
        "guys": 24,
        "decided": 11,
        "extra": 15,
        "sounds": 22,
        "gonna": 106,
        "mention": 8,
        "worry": 42,
        "figure": 26,
        "somehow": 7,
        "love": 40,
        "choose": 11,
        "disappointed": 8,
        "special": 25,
        "favors": 6,
        "huh": 42,
        "comfortable": 6,
        "close": 17,
        "cloud": 6,
        "heh": 17,
        "ow": 7,
        "giggles": 6,
        "grand": 6,
        "else": 41,
        "kidding": 8,
        "giving": 10,
        "easier": 7,
        "tried": 22,
        "gifts": 6,
        "dear": 18,
        "friendship": 162,
        "feel": 38,
        "nope": 7,
        "mind": 30,
        "possibly": 7,
        "enjoy": 9,
        "ready": 43,
        "set": 18,
        "welcome": 22,
        "everypony": 106,
        "honor": 7,
        "count": 8,
        "exactly": 38,
        "urgh": 6,
        "scary": 10,
        "little": 91,
        "earth": 7,
        "hey": 38,
        "met": 12,
        "talk": 37,
        "except": 7,
        "soon": 18,
        "happened": 58,
        "upset": 16,
        "tree": 24,
        "care": 43,
        "caused": 6,
        "plenty": 6,
        "apple": 24,
        "family": 25,
        "anypony": 36,
        "maybe": 100,
        "answer": 10,
        "trouble": 19,
        "ourselves": 7,
        "bit": 19,
        "jealous": 8,
        "gilda": 6,
        "goes": 12,
        "practice": 11,
        "talents": 7,
        "lots": 6,
        "unicorn": 11,
        "trixie": 22,
        "thinking": 18,
        "especially": 7,
        "risk": 6,
        "seen": 31,
        "hate": 9,
        "looking": 32,
        "reading": 38,
        "lesson": 31,
        "clean": 10,
        "mess": 13,
        "twenty": 6,
        "afraid": 20,
        "helped": 15,
        "realize": 12,
        "proud": 14,
        "standing": 6,
        "try": 42,
        "yourself": 17,
        "smoke": 10,
        "according": 9,
        "mission": 9,
        "fail": 10,
        "covered": 6,
        "hundred": 21,
        "ahead": 12,
        "meet": 14,
        "top": 8,
        "animals": 13,
        "gone": 16,
        "move": 21,
        "laughing": 11,
        "matter": 12,
        "creatures": 8,
        "map": 37,
        "huge": 8,
        "rock": 8,
        "wings": 11,
        "create": 8,
        "wake": 8,
        "able": 23,
        "understand": 36,
        "kinds": 6,
        "dragons": 12,
        "probably": 23,
        "awake": 6,
        "introduce": 7,
        "dark": 11,
        "getting": 38,
        "report": 8,
        "taught": 19,
        "lose": 8,
        "amazing": 41,
        "magical": 21,
        "home": 44,
        "storm": 9,
        "stay": 29,
        "business": 9,
        "tonight": 11,
        "totally": 16,
        "slumber": 11,
        "party": 54,
        "fantastic": 6,
        "table": 10,
        "waiting": 7,
        "chance": 28,
        "exciting": 10,
        "fun": 46,
        "giggle": 9,
        "safe": 13,
        "truth": 12,
        "dare": 7,
        "honest": 7,
        "question": 9,
        "whatever": 25,
        "fight": 14,
        "call": 11,
        "ruined": 7,
        "middle": 6,
        "section": 6,
        "laugh": 9,
        "questions": 7,
        "left": 25,
        "finally": 17,
        "win": 6,
        "believe": 54,
        "common": 7,
        "week": 18,
        "month": 7,
        "bet": 13,
        "cut": 7,
        "fashion": 6,
        "choice": 7,
        "books": 41,
        "land": 7,
        "live": 10,
        "zecora": 25,
        "normal": 8,
        "comes": 11,
        "visit": 27,
        "free": 9,
        "bloom": 16,
        "sighs": 51,
        "brother": 16,
        "real": 33,
        "meant": 18,
        "power": 26,
        "dream": 7,
        "horn": 6,
        "cure": 8,
        "word": 7,
        "start": 26,
        "hurry": 9,
        "sound": 7,
        "soup": 7,
        "evil": 11,
        "sweetie": 8,
        "saying": 13,
        "save": 13,
        "jokes": 8,
        "natural": 6,
        "funny": 15,
        "forever": 8,
        "perfect": 37,
        "hang": 10,
        "cake": 20,
        "hooves": 16,
        "besides": 9,
        "minute": 10,
        "ago": 12,
        "hours": 6,
        "control": 19,
        "nopony": 19,
        "telling": 12,
        "missing": 14,
        "lost": 16,
        "forget": 10,
        "cast": 12,
        "spell": 78,
        "plan": 21,
        "trip": 17,
        "sometimes": 6,
        "solution": 7,
        "sense": 23,
        "handle": 18,
        "winter": 14,
        "spring": 6,
        "organized": 6,
        "team": 15,
        "wonder": 8,
        "gosh": 13,
        "clue": 7,
        "clouds": 6,
        "begin": 6,
        "break": 18,
        "stuff": 9,
        "life": 22,
        "late": 16,
        "checklist": 8,
        "teamwork": 6,
        "follow": 8,
        "cutie": 45,
        "mark": 32,
        "lucky": 6,
        "experience": 8,
        "talking": 26,
        "lead": 8,
        "excited": 13,
        "race": 13,
        "remember": 35,
        "game": 7,
        "finish": 13,
        "dress": 8,
        "fix": 13,
        "sweet": 8,
        "knowing": 9,
        "absolutely": 9,
        "dresses": 6,
        "eyes": 9,
        "attention": 13,
        "wide": 6,
        "world": 21,
        "fall": 6,
        "honestly": 10,
        "future": 37,
        "happens": 14,
        "makes": 21,
        "information": 8,
        "explain": 14,
        "happening": 10,
        "research": 15,
        "bottom": 6,
        "teach": 18,
        "flower": 7,
        "eye": 14,
        "promise": 17,
        "calm": 12,
        "doozy": 6,
        "luck": 13,
        "anymore": 15,
        "takes": 7,
        "helping": 15,
        "rainboom": 7,
        "pull": 7,
        "flight": 6,
        "fly": 15,
        "days": 16,
        "test": 26,
        "walk": 7,
        "seven": 11,
        "everfree": 8,
        "forest": 8,
        "favorite": 13,
        "instead": 10,
        "stick": 8,
        "congratulations": 7,
        "started": 14,
        "filled": 6,
        "write": 12,
        "somepony": 32,
        "using": 9,
        "hurt": 12,
        "pick": 7,
        "feelings": 9,
        "trust": 18,
        "model": 6,
        "obviously": 9,
        "ha": 9,
        "secret": 8,
        "share": 12,
        "goodness": 11,
        "ya": 8,
        "train": 6,
        "sit": 8,
        "worst": 7,
        "spent": 6,
        "hi": 17,
        "pants": 7,
        "throw": 8,
        "unless": 10,
        "deal": 12,
        "step": 6,
        "fault": 15,
        "filly": 6,
        "voiceover": 7,
        "learning": 13,
        "school": 60,
        "unicorns": 6,
        "pass": 14,
        "entire": 12,
        "feeling": 9,
        "quill": 7,
        "ink": 6,
        "assistant": 10,
        "forgot": 6,
        "speaking": 7,
        "owlowiscious": 9,
        "tired": 6,
        "headed": 7,
        "truly": 7,
        "wish": 18,
        "corner": 6,
        "spend": 16,
        "trick": 6,
        "worse": 12,
        "failed": 6,
        "connected": 8,
        "honored": 10,
        "discord": 37,
        "head": 16,
        "suppose": 14,
        "playing": 9,
        "defeat": 6,
        "figured": 9,
        "pack": 6,
        "written": 7,
        "lived": 6,
        "friendships": 10,
        "fighting": 12,
        "whispering": 14,
        "hold": 14,
        "worth": 7,
        "schedule": 12,
        "planning": 7,
        "add": 6,
        "usually": 9,
        "seriously": 6,
        "students": 22,
        "solve": 11,
        "alright": 23,
        "groans": 12,
        "mine": 6,
        "age": 6,
        "play": 17,
        "missed": 10,
        "star": 46,
        "swirl": 36,
        "bearded": 15,
        "history": 21,
        "hoof": 11,
        "spells": 8,
        "luna": 34,
        "change": 15,
        "thousand": 7,
        "actual": 7,
        "changed": 14,
        "watch": 6,
        "lecture": 7,
        "definitely": 9,
        "sister": 8,
        "marks": 15,
        "perform": 6,
        "planned": 7,
        "notes": 7,
        "act": 9,
        "miss": 14,
        "outside": 14,
        "finished": 7,
        "half": 9,
        "anyway": 9,
        "voice": 9,
        "eight": 10,
        "candy": 7,
        "minutes": 7,
        "feels": 9,
        "hearts": 8,
        "stopped": 6,
        "answers": 6,
        "flim": 8,
        "flam": 8,
        "quality": 6,
        "daring": 9,
        "brought": 13,
        "yesterday": 6,
        "quest": 7,
        "holiday": 8,
        "recipe": 7,
        "seeing": 10,
        "meeting": 9,
        "tuesday": 8,
        "pegasi": 7,
        "spread": 9,
        "teeth": 7,
        "sign": 8,
        "nine": 7,
        "hushed": 37,
        "exhales": 8,
        "wing": 18,
        "speak": 6,
        "water": 6,
        "gabby": 7,
        "class": 19,
        "wedding": 9,
        "role": 8,
        "shining": 27,
        "armor": 24,
        "starting": 10,
        "field": 7,
        "cadance": 43,
        "caught": 6,
        "notice": 7,
        "neither": 11,
        "echoing": 7,
        "plans": 6,
        "queen": 9,
        "ahem": 8,
        "crystal": 46,
        "empire": 24,
        "studied": 6,
        "protect": 8,
        "prepared": 11,
        "skills": 8,
        "king": 20,
        "sombra": 7,
        "faire": 7,
        "invite": 6,
        "claw": 7,
        "door": 9,
        "mistake": 8,
        "celebrate": 8,
        "ones": 6,
        "strange": 8,
        "beat": 11,
        "alicorn": 10,
        "amulet": 14,
        "hmmm": 7,
        "busy": 12,
        "dinner": 7,
        "games": 8,
        "breathes": 7,
        "tour": 6,
        "remind": 10,
        "flying": 11,
        "chest": 6,
        "perfectly": 7,
        "hoo": 7,
        "journal": 17,
        "shadows": 7,
        "bats": 6,
        "news": 10,
        "official": 7,
        "stage": 6,
        "third": 7,
        "join": 10,
        "maud": 12,
        "knowledge": 6,
        "unique": 8,
        "trade": 6,
        "shot": 6,
        "lessons": 17,
        "tirek": 10,
        "key": 7,
        "strong": 7,
        "village": 10,
        "starlight": 64,
        "griffonstone": 9,
        "griffon": 6,
        "griffons": 6,
        "narrating": 6,
        "idol": 6,
        "mountains": 6,
        "plus": 6,
        "yawns": 7,
        "yakyakistan": 8,
        "imagine": 7,
        "yaks": 8,
        "surprise": 10,
        "dancer": 10,
        "spending": 6,
        "princesses": 6,
        "prize": 7,
        "aunt": 12,
        "warming": 17,
        "eve": 8,
        "amplified": 6,
        "festival": 6,
        "pupil": 6,
        "sunburst": 7,
        "boat": 13,
        "ember": 9,
        "sweep": 13,
        "flurry": 22,
        "changeling": 6,
        "teaching": 6,
        "retreat": 8,
        "foals": 6,
        "cruise": 9,
        "activities": 6,
        "dad": 6,
        "pillars": 10,
        "limbo": 8,
        "tempest": 6,
        "eea": 9,
        "chancellor": 11,
        "classes": 6,
        "mount": 6,
        "aris": 6,
        "hippogriffs": 8,
        "cozy": 7,
        "pudding": 6,
        "yovidaphone": 6,
        "rockhoof": 12
    },
    "applejack": {
        "howdy": 14,
        "miss": 11,
        "twilight": 95,
        "applejack": 9,
        "sweet": 27,
        "apple": 185,
        "acres": 15,
        "friends": 36,
        "care": 17,
        "everypony": 51,
        "family": 55,
        "delicious": 11,
        "caramel": 7,
        "apples": 69,
        "breath": 9,
        "mcintosh": 10,
        "bloom": 63,
        "granny": 60,
        "smith": 25,
        "sugarcube": 31,
        "muffled": 10,
        "whoa": 32,
        "friend": 20,
        "ours": 7,
        "equestria": 32,
        "rainbow": 59,
        "quit": 6,
        "hold": 24,
        "promise": 9,
        "safe": 8,
        "listen": 14,
        "honest": 22,
        "truth": 19,
        "yee": 19,
        "haw": 19,
        "little": 89,
        "oh": 103,
        "wait": 30,
        "mud": 6,
        "hay": 16,
        "supposed": 21,
        "mean": 55,
        "okay": 53,
        "lot": 22,
        "reckon": 15,
        "friendship": 38,
        "hoo": 20,
        "nice": 27,
        "love": 19,
        "stand": 6,
        "set": 9,
        "ponies": 56,
        "home": 38,
        "idea": 24,
        "business": 10,
        "money": 7,
        "left": 22,
        "dash": 47,
        "told": 32,
        "busy": 16,
        "help": 71,
        "harvest": 7,
        "doing": 7,
        "pony": 61,
        "minute": 17,
        "yeah": 50,
        "hoof": 13,
        "farm": 20,
        "fix": 10,
        "try": 25,
        "funny": 7,
        "somepony": 25,
        "pie": 62,
        "fritters": 6,
        "uh": 168,
        "yes": 21,
        "maybe": 59,
        "else": 25,
        "feel": 34,
        "bad": 23,
        "spike": 37,
        "boy": 8,
        "handle": 8,
        "bit": 21,
        "eyes": 7,
        "brother": 6,
        "rest": 19,
        "yourself": 15,
        "orchard": 9,
        "sorry": 54,
        "job": 15,
        "sister": 21,
        "remember": 20,
        "gonna": 124,
        "themselves": 6,
        "outta": 6,
        "trees": 8,
        "hey": 37,
        "move": 10,
        "winona": 9,
        "girl": 6,
        "grunts": 8,
        "understand": 8,
        "time": 95,
        "ponyville": 33,
        "yawn": 6,
        "sigh": 15,
        "thank": 12,
        "heh": 53,
        "look": 49,
        "stuff": 15,
        "thanks": 16,
        "gasp": 20,
        "sell": 7,
        "reunion": 11,
        "actually": 17,
        "live": 7,
        "own": 17,
        "means": 17,
        "worry": 16,
        "none": 9,
        "fine": 24,
        "prove": 7,
        "excuse": 7,
        "buck": 8,
        "mite": 6,
        "guess": 48,
        "welcome": 6,
        "wanna": 29,
        "talk": 20,
        "gotta": 45,
        "pinkie": 83,
        "pies": 10,
        "eye": 6,
        "perfect": 14,
        "fancy": 12,
        "hot": 6,
        "huh": 51,
        "answer": 6,
        "har": 7,
        "grunt": 7,
        "ugh": 13,
        "times": 10,
        "nopony": 14,
        "critters": 6,
        "finish": 10,
        "ha": 10,
        "please": 14,
        "break": 7,
        "ya": 71,
        "girls": 9,
        "awful": 8,
        "town": 14,
        "real": 41,
        "five": 10,
        "heard": 15,
        "hah": 7,
        "play": 12,
        "goes": 7,
        "school": 7,
        "filly": 14,
        "unicorn": 6,
        "hat": 9,
        "magic": 12,
        "proud": 12,
        "mm": 6,
        "hmm": 13,
        "name": 11,
        "dragon": 6,
        "looks": 34,
        "pretty": 23,
        "cold": 7,
        "split": 8,
        "aw": 25,
        "scared": 8,
        "tarnation": 20,
        "rarity": 74,
        "mess": 7,
        "anypony": 25,
        "yer": 11,
        "fast": 10,
        "inside": 8,
        "tree": 12,
        "spend": 6,
        "darn": 9,
        "hooves": 9,
        "quick": 10,
        "course": 17,
        "meet": 11,
        "tell": 53,
        "crazy": 10,
        "story": 7,
        "stop": 25,
        "change": 9,
        "mane": 8,
        "happy": 15,
        "rodeo": 11,
        "comes": 9,
        "happen": 9,
        "um": 12,
        "call": 12,
        "tried": 9,
        "mighty": 20,
        "hard": 18,
        "barn": 18,
        "reason": 13,
        "started": 15,
        "brought": 9,
        "born": 7,
        "seen": 19,
        "stay": 13,
        "hear": 22,
        "learn": 9,
        "true": 16,
        "voice": 8,
        "hate": 7,
        "wrong": 13,
        "celestia": 15,
        "easy": 10,
        "sis": 9,
        "fluttershy": 34,
        "figure": 12,
        "scoffs": 6,
        "straight": 7,
        "alright": 24,
        "lead": 8,
        "forget": 15,
        "focus": 6,
        "head": 14,
        "eat": 9,
        "food": 10,
        "tomorrow": 13,
        "start": 17,
        "strong": 7,
        "team": 10,
        "lost": 9,
        "cutie": 21,
        "mark": 16,
        "class": 6,
        "run": 23,
        "deal": 9,
        "am": 35,
        "charge": 8,
        "days": 10,
        "party": 14,
        "bet": 16,
        "glad": 15,
        "wee": 15,
        "wow": 12,
        "fun": 17,
        "wings": 8,
        "win": 13,
        "race": 8,
        "ready": 16,
        "turkey": 6,
        "believe": 22,
        "catch": 8,
        "mind": 13,
        "princess": 32,
        "makes": 11,
        "sense": 11,
        "shoot": 8,
        "plumb": 7,
        "leave": 12,
        "learned": 6,
        "hope": 19,
        "wonder": 11,
        "sounds": 9,
        "plan": 7,
        "save": 12,
        "whew": 9,
        "ride": 7,
        "kick": 6,
        "appleloosa": 11,
        "braeburn": 12,
        "cousin": 10,
        "special": 6,
        "day": 38,
        "hungry": 7,
        "voiceover": 11,
        "life": 15,
        "manehattan": 10,
        "meant": 6,
        "beat": 9,
        "pick": 8,
        "yup": 13,
        "clothes": 9,
        "bring": 13,
        "plenty": 15,
        "night": 14,
        "trust": 9,
        "worth": 8,
        "discord": 8,
        "found": 7,
        "absolutely": 6,
        "called": 8,
        "happened": 12,
        "clears": 7,
        "throat": 7,
        "games": 7,
        "exactly": 19,
        "chores": 10,
        "ahead": 8,
        "chuckles": 13,
        "figured": 6,
        "mac": 25,
        "finally": 9,
        "grunting": 7,
        "cure": 8,
        "excited": 6,
        "matter": 9,
        "laughs": 9,
        "gasps": 13,
        "holes": 7,
        "map": 17,
        "calm": 7,
        "water": 7,
        "pegasus": 9,
        "shucks": 9,
        "breakfast": 9,
        "sighs": 49,
        "heck": 7,
        "hide": 8,
        "cider": 21,
        "takes": 7,
        "agreed": 6,
        "serious": 7,
        "chance": 10,
        "pack": 8,
        "gone": 10,
        "count": 7,
        "hushed": 18,
        "neither": 6,
        "forever": 7,
        "check": 12,
        "probably": 13,
        "crystal": 18,
        "kinda": 10,
        "able": 17,
        "empire": 9,
        "heart": 8,
        "fake": 6,
        "spirit": 6,
        "power": 6,
        "traditional": 9,
        "train": 8,
        "sleep": 6,
        "scootaloo": 6,
        "realize": 6,
        "twice": 7,
        "memories": 7,
        "raise": 8,
        "definitely": 6,
        "timberwolf": 6,
        "stuck": 7,
        "cadance": 6,
        "trouble": 9,
        "suppose": 11,
        "close": 6,
        "castle": 6,
        "vampire": 6,
        "bats": 12,
        "narrating": 14,
        "goldie": 9,
        "worse": 10,
        "festival": 7,
        "teach": 6,
        "fashion": 13,
        "accent": 7,
        "hang": 6,
        "cart": 10,
        "flim": 9,
        "flam": 8,
        "tonic": 11,
        "extra": 7,
        "village": 8,
        "nope": 9,
        "families": 6,
        "flag": 6,
        "traditions": 6,
        "countess": 6,
        "coloratura": 10,
        "rara": 17,
        "starlight": 11,
        "spa": 8,
        "hour": 6,
        "steam": 11,
        "game": 7,
        "las": 6,
        "gladmane": 6,
        "mechanically": 9,
        "sea": 8,
        "dog": 6,
        "adventure": 7,
        "rockhoof": 13,
        "teacher": 6
    },
    "rarity": {
        "oh": 484,
        "goodness": 16,
        "moment": 15,
        "please": 62,
        "yes": 120,
        "sparkle": 8,
        "rarity": 40,
        "um": 16,
        "help": 66,
        "darling": 107,
        "whatever": 19,
        "happened": 14,
        "hair": 12,
        "uh": 96,
        "dear": 38,
        "huh": 15,
        "canterlot": 49,
        "am": 68,
        "wait": 23,
        "hear": 20,
        "gonna": 7,
        "friends": 32,
        "thinking": 11,
        "gone": 11,
        "ugh": 25,
        "heavens": 9,
        "look": 80,
        "dreadful": 9,
        "eyes": 6,
        "rest": 9,
        "mean": 32,
        "course": 81,
        "lovely": 28,
        "scales": 7,
        "mane": 26,
        "fabulous": 38,
        "ruined": 14,
        "beautiful": 25,
        "simply": 52,
        "crime": 8,
        "fine": 17,
        "season": 7,
        "besides": 6,
        "thank": 55,
        "ooh": 70,
        "gasp": 24,
        "gala": 16,
        "design": 10,
        "opportunity": 6,
        "truly": 6,
        "meet": 15,
        "wonder": 7,
        "mare": 7,
        "guess": 13,
        "simple": 6,
        "pony": 67,
        "little": 73,
        "ponyville": 32,
        "princess": 36,
        "celestia": 14,
        "style": 15,
        "unicorn": 12,
        "magnificent": 6,
        "hoof": 19,
        "royal": 13,
        "giggles": 18,
        "twilight": 74,
        "believe": 30,
        "pinkie": 57,
        "pie": 40,
        "party": 28,
        "true": 15,
        "love": 42,
        "hmph": 7,
        "spike": 68,
        "outfit": 16,
        "hat": 14,
        "laughs": 22,
        "grand": 14,
        "happen": 11,
        "ensemble": 10,
        "own": 16,
        "attention": 10,
        "finally": 11,
        "equestria": 39,
        "ah": 33,
        "nervous": 9,
        "try": 21,
        "treat": 9,
        "mayor": 6,
        "ready": 19,
        "friend": 35,
        "rainbow": 65,
        "dash": 56,
        "rare": 7,
        "favorite": 20,
        "perform": 8,
        "magic": 18,
        "applejack": 91,
        "beauty": 16,
        "called": 16,
        "terrible": 12,
        "mm": 17,
        "hmm": 35,
        "meant": 8,
        "talk": 11,
        "getting": 27,
        "sleep": 7,
        "brought": 6,
        "scarf": 6,
        "jewels": 10,
        "play": 11,
        "able": 14,
        "games": 8,
        "row": 7,
        "tell": 48,
        "obviously": 12,
        "girls": 17,
        "sorry": 52,
        "clears": 18,
        "throat": 18,
        "possibly": 21,
        "head": 11,
        "home": 15,
        "silly": 18,
        "hundred": 7,
        "happy": 13,
        "eye": 9,
        "ridiculous": 11,
        "perfect": 46,
        "somepony": 38,
        "absolute": 6,
        "mess": 7,
        "town": 12,
        "imagine": 9,
        "ponies": 45,
        "evening": 6,
        "ruin": 8,
        "day": 32,
        "coming": 14,
        "hooves": 22,
        "laugh": 10,
        "heh": 10,
        "indeed": 9,
        "completely": 10,
        "mind": 18,
        "stay": 20,
        "night": 16,
        "reading": 14,
        "afraid": 14,
        "sigh": 10,
        "rude": 6,
        "anypony": 17,
        "matter": 17,
        "difficult": 7,
        "word": 8,
        "heard": 14,
        "story": 7,
        "everypony": 38,
        "excuse": 10,
        "dare": 8,
        "change": 11,
        "truth": 8,
        "stand": 13,
        "pay": 6,
        "okay": 25,
        "dress": 40,
        "comes": 6,
        "started": 11,
        "fix": 7,
        "mmm": 7,
        "trying": 10,
        "stop": 36,
        "tried": 6,
        "awful": 9,
        "thanks": 13,
        "world": 7,
        "maybe": 28,
        "else": 22,
        "worse": 6,
        "left": 14,
        "wrong": 12,
        "aah": 7,
        "doing": 37,
        "horrible": 7,
        "nice": 13,
        "life": 15,
        "adorable": 8,
        "boutique": 24,
        "busy": 7,
        "time": 113,
        "real": 10,
        "disaster": 8,
        "inside": 8,
        "food": 11,
        "finest": 6,
        "live": 7,
        "bit": 26,
        "ribbon": 9,
        "oooh": 7,
        "careful": 6,
        "spa": 17,
        "ha": 11,
        "bad": 16,
        "opalescence": 6,
        "stunning": 7,
        "gown": 13,
        "opal": 14,
        "move": 6,
        "wear": 10,
        "insist": 6,
        "serious": 7,
        "absolutely": 29,
        "deal": 6,
        "idea": 23,
        "fluttershy": 57,
        "hold": 8,
        "fashion": 48,
        "wonderful": 15,
        "business": 7,
        "fun": 15,
        "sound": 10,
        "hard": 21,
        "fabric": 11,
        "color": 9,
        "outfits": 7,
        "perfectly": 6,
        "unique": 6,
        "forever": 12,
        "amazing": 11,
        "plenty": 8,
        "worry": 21,
        "gotten": 8,
        "saying": 15,
        "choice": 6,
        "tonight": 16,
        "sewing": 7,
        "hour": 10,
        "forget": 13,
        "shine": 6,
        "remember": 13,
        "dresses": 12,
        "exactly": 22,
        "relax": 6,
        "squeals": 8,
        "means": 15,
        "sobbing": 11,
        "leave": 12,
        "supposed": 11,
        "listen": 6,
        "poor": 8,
        "tree": 6,
        "job": 6,
        "imagined": 8,
        "spell": 6,
        "wings": 8,
        "adore": 6,
        "ahead": 7,
        "pfft": 8,
        "perfection": 6,
        "hope": 22,
        "fly": 8,
        "city": 11,
        "talking": 11,
        "panting": 6,
        "lost": 16,
        "win": 6,
        "learned": 8,
        "understand": 27,
        "lot": 11,
        "gasps": 72,
        "looks": 15,
        "cutie": 6,
        "sweetie": 48,
        "handle": 8,
        "special": 12,
        "tomorrow": 12,
        "morning": 9,
        "gold": 6,
        "silk": 10,
        "touch": 8,
        "hello": 11,
        "belle": 38,
        "watch": 8,
        "sister": 20,
        "suppose": 23,
        "hmmm": 7,
        "admit": 7,
        "shop": 15,
        "clean": 6,
        "told": 9,
        "welcome": 12,
        "carousel": 11,
        "chic": 6,
        "sapphire": 7,
        "shores": 6,
        "name": 12,
        "miss": 14,
        "prepare": 6,
        "yourself": 11,
        "la": 6,
        "couture": 12,
        "found": 11,
        "pardon": 10,
        "lady": 6,
        "costumes": 15,
        "gems": 8,
        "bring": 15,
        "cart": 8,
        "waiting": 7,
        "start": 22,
        "strange": 6,
        "hurry": 6,
        "dirt": 7,
        "save": 9,
        "proper": 6,
        "care": 7,
        "mystery": 6,
        "breath": 6,
        "makes": 16,
        "water": 8,
        "terribly": 10,
        "appreciate": 10,
        "wish": 14,
        "call": 16,
        "entire": 11,
        "hate": 7,
        "late": 6,
        "wearing": 11,
        "photo": 14,
        "finish": 20,
        "marvelous": 8,
        "clothes": 6,
        "model": 6,
        "huge": 7,
        "nopony": 12,
        "agree": 8,
        "feel": 30,
        "hm": 13,
        "attitude": 6,
        "star": 6,
        "hoping": 6,
        "chance": 17,
        "excited": 21,
        "designs": 7,
        "spend": 8,
        "promise": 9,
        "looking": 18,
        "apple": 16,
        "baby": 9,
        "crying": 6,
        "loud": 6,
        "quiet": 6,
        "speak": 7,
        "ow": 6,
        "delicious": 6,
        "figure": 7,
        "mine": 13,
        "taking": 8,
        "reason": 6,
        "explain": 9,
        "divine": 10,
        "delightful": 8,
        "dragon": 9,
        "afternoon": 10,
        "dirty": 6,
        "sweet": 14,
        "seen": 8,
        "birthday": 6,
        "ahem": 14,
        "lose": 8,
        "elements": 6,
        "window": 9,
        "gem": 8,
        "worst": 7,
        "drama": 7,
        "sniffs": 8,
        "week": 9,
        "days": 10,
        "designer": 10,
        "trouble": 7,
        "inspiration": 7,
        "finished": 6,
        "line": 17,
        "honestly": 12,
        "consider": 6,
        "costume": 9,
        "castle": 21,
        "sounds": 14,
        "flow": 6,
        "set": 8,
        "event": 6,
        "sighs": 36,
        "glad": 12,
        "nervously": 17,
        "cake": 14,
        "running": 7,
        "check": 7,
        "hushed": 29,
        "muffled": 13,
        "visit": 10,
        "normal": 14,
        "spikey": 12,
        "wikey": 10,
        "inspired": 10,
        "generosity": 7,
        "generous": 6,
        "impossible": 7,
        "likes": 7,
        "finding": 7,
        "worth": 10,
        "rock": 7,
        "filly": 11,
        "times": 6,
        "apples": 8,
        "horrid": 6,
        "book": 15,
        "hoo": 8,
        "dragons": 7,
        "dream": 7,
        "plan": 7,
        "actually": 15,
        "gabby": 6,
        "gums": 6,
        "funny": 6,
        "read": 9,
        "gorgeous": 16,
        "words": 7,
        "crystal": 6,
        "creating": 8,
        "zesty": 14,
        "cucumber": 6,
        "sandwiches": 6,
        "wide": 6,
        "ones": 7,
        "farm": 6,
        "run": 7,
        "grunts": 7,
        "soon": 11,
        "manehattan": 21,
        "bold": 7,
        "key": 6,
        "shopping": 6,
        "ta": 11,
        "chuckles": 10,
        "collection": 12,
        "friendship": 20,
        "spirit": 7,
        "festival": 12,
        "country": 10,
        "vision": 7,
        "accent": 8,
        "voice": 18,
        "tones": 9,
        "share": 6,
        "zecora": 12,
        "nightmare": 6,
        "maud": 18,
        "vintage": 6,
        "piece": 6,
        "creative": 11,
        "chuckling": 6,
        "sassy": 11,
        "saddles": 6,
        "rules": 6,
        "break": 7,
        "shadow": 7,
        "spade": 6,
        "pick": 7,
        "spitfire": 8,
        "narrating": 24,
        "chocolate": 7,
        "map": 8,
        "surprise": 6,
        "judge": 6,
        "pouch": 11,
        "restaurant": 10,
        "cannon": 7,
        "steam": 6,
        "enjoy": 9,
        "mechanically": 9,
        "cruise": 7,
        "luxury": 6,
        "designers": 7,
        "mwah": 6,
        "mistmane": 7,
        "school": 10,
        "shoot": 7,
        "shampoo": 6,
        "loudly": 12
    },
    "pinkie pie": {
        "surprise": 31,
        "hi": 18,
        "pinkie": 81,
        "pie": 99,
        "threw": 6,
        "party": 157,
        "ya": 12,
        "huh": 53,
        "silly": 32,
        "welcome": 34,
        "mean": 64,
        "remember": 14,
        "deep": 15,
        "gasp": 24,
        "means": 29,
        "everypony": 59,
        "ponyville": 49,
        "met": 7,
        "friends": 79,
        "sad": 9,
        "idea": 30,
        "throw": 15,
        "super": 52,
        "duper": 15,
        "lots": 13,
        "aww": 9,
        "happy": 55,
        "crying": 8,
        "ooh": 103,
        "mouth": 11,
        "exciting": 13,
        "excited": 23,
        "except": 7,
        "time": 100,
        "town": 10,
        "top": 8,
        "love": 49,
        "games": 10,
        "harmony": 7,
        "sing": 8,
        "song": 10,
        "voice": 12,
        "whee": 27,
        "candy": 27,
        "apples": 8,
        "oh": 217,
        "girls": 8,
        "little": 37,
        "hide": 7,
        "granny": 9,
        "gotta": 27,
        "stand": 9,
        "laugh": 12,
        "gonna": 92,
        "sighs": 24,
        "yeah": 68,
        "five": 10,
        "look": 70,
        "mine": 8,
        "whoa": 25,
        "blows": 8,
        "nose": 8,
        "hey": 69,
        "help": 60,
        "wait": 79,
        "grand": 19,
        "galloping": 14,
        "gala": 17,
        "amazing": 34,
        "fun": 78,
        "wonderful": 8,
        "equestria": 22,
        "hip": 6,
        "sugar": 7,
        "play": 17,
        "favorite": 14,
        "tail": 12,
        "pony": 77,
        "thank": 25,
        "twilight": 111,
        "gift": 24,
        "yes": 39,
        "taking": 10,
        "canterlot": 7,
        "bestest": 7,
        "friend": 38,
        "bet": 12,
        "extra": 9,
        "celebrate": 8,
        "cupcakes": 12,
        "laughter": 6,
        "makes": 20,
        "sound": 6,
        "run": 11,
        "sugarcube": 7,
        "corner": 8,
        "applejack": 56,
        "free": 9,
        "woo": 35,
        "ooo": 6,
        "fine": 20,
        "cake": 65,
        "stop": 36,
        "chocolate": 16,
        "baking": 8,
        "flour": 7,
        "delicious": 10,
        "spike": 18,
        "hoof": 12,
        "flying": 6,
        "rainbow": 110,
        "dash": 87,
        "hit": 9,
        "whoo": 14,
        "tell": 59,
        "looking": 11,
        "seen": 18,
        "okay": 73,
        "thanks": 23,
        "anyway": 11,
        "totally": 19,
        "promise": 13,
        "left": 12,
        "hmm": 19,
        "maybe": 50,
        "uh": 79,
        "perfect": 27,
        "laughing": 21,
        "getting": 13,
        "mmm": 15,
        "gold": 6,
        "fluttershy": 50,
        "chuckles": 6,
        "mind": 12,
        "giggles": 27,
        "close": 11,
        "day": 65,
        "lot": 16,
        "griffon": 7,
        "laughs": 17,
        "awesome": 15,
        "gilda": 10,
        "game": 15,
        "wow": 24,
        "guys": 23,
        "beat": 11,
        "hair": 6,
        "um": 17,
        "balloons": 14,
        "told": 13,
        "actually": 17,
        "aw": 16,
        "poor": 6,
        "funny": 23,
        "guess": 26,
        "worry": 19,
        "pretty": 34,
        "head": 8,
        "care": 14,
        "parties": 10,
        "hope": 16,
        "feel": 22,
        "eye": 14,
        "meet": 13,
        "dear": 6,
        "please": 31,
        "yourself": 11,
        "wonder": 6,
        "watch": 7,
        "definitely": 11,
        "ahead": 9,
        "wrong": 15,
        "hang": 7,
        "hard": 11,
        "finish": 7,
        "celebration": 6,
        "seven": 8,
        "doctor": 6,
        "hoo": 35,
        "win": 11,
        "hop": 8,
        "skip": 9,
        "jump": 13,
        "move": 9,
        "rump": 7,
        "try": 16,
        "exactly": 20,
        "heh": 7,
        "zecora": 7,
        "doing": 26,
        "evil": 10,
        "stuff": 11,
        "eyes": 6,
        "tasty": 8,
        "heard": 14,
        "ah": 24,
        "am": 41,
        "gone": 8,
        "mm": 8,
        "gosh": 17,
        "able": 8,
        "talk": 19,
        "talking": 13,
        "anymore": 7,
        "somepony": 24,
        "king": 8,
        "queen": 7,
        "princess": 30,
        "home": 16,
        "ugh": 14,
        "kidding": 7,
        "anypony": 22,
        "hello": 6,
        "rarity": 52,
        "soon": 12,
        "real": 18,
        "answer": 6,
        "drop": 7,
        "follow": 6,
        "lost": 8,
        "trying": 14,
        "listen": 7,
        "save": 11,
        "happened": 11,
        "hooves": 19,
        "tried": 6,
        "understand": 11,
        "tomorrow": 11,
        "comes": 8,
        "probably": 11,
        "cut": 6,
        "rest": 6,
        "team": 8,
        "ice": 14,
        "easy": 21,
        "ha": 23,
        "wanna": 28,
        "eating": 11,
        "helping": 6,
        "bit": 13,
        "oooh": 12,
        "chomp": 10,
        "yay": 13,
        "forget": 13,
        "running": 10,
        "leaves": 7,
        "official": 14,
        "ready": 19,
        "ponies": 45,
        "minutes": 6,
        "name": 15,
        "eat": 26,
        "check": 11,
        "fast": 9,
        "half": 11,
        "speaking": 6,
        "strong": 6,
        "hundred": 7,
        "upset": 6,
        "pick": 16,
        "nice": 13,
        "looks": 16,
        "found": 24,
        "pickle": 8,
        "history": 7,
        "believe": 23,
        "days": 10,
        "sorry": 37,
        "twitch": 10,
        "sense": 16,
        "telling": 7,
        "start": 13,
        "la": 63,
        "else": 15,
        "lucky": 6,
        "happen": 12,
        "pet": 6,
        "gummy": 28,
        "teeth": 6,
        "magic": 12,
        "true": 12,
        "sometimes": 10,
        "random": 6,
        "times": 10,
        "call": 11,
        "beautiful": 7,
        "coming": 16,
        "thinking": 11,
        "usually": 7,
        "okie": 8,
        "dokie": 8,
        "hold": 6,
        "hu": 6,
        "bu": 25,
        "whatcha": 8,
        "secret": 13,
        "dunno": 7,
        "whatever": 11,
        "doozy": 7,
        "ho": 8,
        "oo": 17,
        "pegasus": 7,
        "sounds": 16,
        "rainboom": 7,
        "cool": 12,
        "boom": 6,
        "twenty": 7,
        "heart": 10,
        "fly": 6,
        "stick": 6,
        "cupcake": 14,
        "word": 8,
        "promised": 6,
        "forever": 19,
        "sigh": 6,
        "whispering": 13,
        "tree": 9,
        "ahh": 7,
        "fault": 8,
        "course": 24,
        "cutie": 8,
        "voiceover": 6,
        "rock": 32,
        "rocks": 14,
        "smile": 13,
        "smiles": 6,
        "story": 11,
        "started": 13,
        "cookies": 7,
        "nope": 16,
        "singing": 6,
        "apple": 18,
        "dance": 6,
        "birthday": 39,
        "stay": 14,
        "cream": 15,
        "books": 11,
        "read": 11,
        "afternoon": 9,
        "saying": 13,
        "bring": 10,
        "starting": 7,
        "inside": 8,
        "bad": 13,
        "sir": 6,
        "own": 15,
        "missing": 6,
        "playing": 13,
        "fancy": 8,
        "prince": 17,
        "sister": 29,
        "pink": 13,
        "hate": 8,
        "chicken": 6,
        "nightmare": 7,
        "moon": 7,
        "hear": 12,
        "muffled": 8,
        "cakes": 8,
        "figured": 8,
        "leave": 13,
        "cannon": 15,
        "special": 12,
        "giving": 9,
        "food": 18,
        "snow": 24,
        "box": 7,
        "reading": 12,
        "map": 8,
        "round": 7,
        "world": 6,
        "minute": 7,
        "baby": 13,
        "gasps": 57,
        "wish": 8,
        "quickly": 14,
        "sniffs": 11,
        "middle": 7,
        "rid": 7,
        "oink": 36,
        "num": 7,
        "goodness": 6,
        "pound": 8,
        "sleep": 6,
        "squeals": 13,
        "celestia": 10,
        "hm": 6,
        "lemme": 6,
        "becoming": 6,
        "terrible": 8,
        "question": 6,
        "kumquat": 7,
        "funnest": 6,
        "barrel": 6,
        "nopony": 12,
        "apology": 12,
        "night": 15,
        "daring": 9,
        "matter": 9,
        "blue": 8,
        "cranky": 29,
        "doodle": 11,
        "guy": 6,
        "friendship": 31,
        "brought": 8,
        "confetti": 11,
        "fix": 10,
        "serious": 6,
        "hmmm": 8,
        "bits": 7,
        "accept": 6,
        "book": 6,
        "seventy": 7,
        "helped": 7,
        "bigger": 6,
        "double": 20,
        "cherry": 6,
        "missed": 8,
        "normal": 6,
        "crystal": 10,
        "finding": 6,
        "weird": 9,
        "mane": 9,
        "star": 6,
        "hushed": 12,
        "marzipan": 8,
        "mascarpone": 8,
        "meringue": 10,
        "madness": 7,
        "dessert": 9,
        "mmmm": 8,
        "chance": 11,
        "door": 6,
        "finally": 8,
        "squee": 6,
        "screams": 6,
        "cute": 9,
        "hole": 6,
        "excuse": 6,
        "plan": 15,
        "pies": 25,
        "pop": 6,
        "eh": 14,
        "phew": 12,
        "package": 6,
        "forgot": 6,
        "angry": 6,
        "boat": 9,
        "castle": 9,
        "admit": 6,
        "trip": 8,
        "hee": 19,
        "family": 16,
        "aah": 6,
        "biggest": 10,
        "planning": 7,
        "cheese": 8,
        "maud": 64,
        "necklaces": 6,
        "loves": 6,
        "wonderbolts": 11,
        "unless": 8,
        "count": 6,
        "news": 6,
        "bake": 9,
        "gulps": 7,
        "flavor": 6,
        "griffonstone": 7,
        "tearing": 7,
        "store": 9,
        "nervous": 10,
        "yaks": 14,
        "yakyakistan": 20,
        "magical": 6,
        "manehattan": 6,
        "rutherford": 13,
        "kinda": 8,
        "picture": 7,
        "warming": 19,
        "bye": 6,
        "boulder": 7,
        "flag": 6,
        "hilarious": 7,
        "starlight": 14,
        "swap": 7,
        "psssd": 8,
        "pouch": 15,
        "red": 7,
        "despondent": 12,
        "wonderbolt": 7,
        "restaurant": 7,
        "mechanically": 6,
        "awful": 6,
        "yak": 13,
        "training": 6,
        "mudbriar": 9
    },
    "rainbow dash": {
        "help": 67,
        "heard": 16,
        "yeah": 172,
        "soon": 6,
        "wonderbolts": 57,
        "gonna": 149,
        "tomorrow": 12,
        "stuff": 22,
        "hey": 81,
        "sky": 15,
        "sounds": 11,
        "leave": 12,
        "ponyville": 46,
        "hanging": 7,
        "chuckles": 10,
        "look": 49,
        "ha": 28,
        "laugh": 7,
        "twilight": 65,
        "wait": 46,
        "hang": 12,
        "princess": 12,
        "pants": 7,
        "forever": 17,
        "elements": 8,
        "huh": 71,
        "whoa": 84,
        "nopony": 16,
        "everypony": 52,
        "fluttershy": 67,
        "quick": 8,
        "pinkie": 96,
        "rarity": 29,
        "time": 89,
        "little": 46,
        "oh": 142,
        "break": 11,
        "duh": 9,
        "scared": 12,
        "yourself": 16,
        "mean": 80,
        "uh": 171,
        "mind": 18,
        "telling": 8,
        "ya": 28,
        "trying": 29,
        "yes": 36,
        "true": 10,
        "real": 19,
        "deal": 16,
        "thank": 13,
        "afraid": 6,
        "friends": 44,
        "ugh": 52,
        "head": 12,
        "aw": 13,
        "crash": 12,
        "talking": 21,
        "busy": 10,
        "happened": 15,
        "hear": 17,
        "extra": 6,
        "ticket": 8,
        "awesome": 105,
        "fly": 38,
        "rainbow": 31,
        "dash": 28,
        "super": 20,
        "speed": 19,
        "filly": 10,
        "flash": 12,
        "ponies": 59,
        "wild": 7,
        "moves": 7,
        "routine": 11,
        "own": 10,
        "chance": 16,
        "dream": 12,
        "minute": 7,
        "maybe": 54,
        "matter": 12,
        "giving": 6,
        "friend": 15,
        "weather": 8,
        "pony": 75,
        "kick": 8,
        "clouds": 14,
        "course": 22,
        "seriously": 18,
        "anypony": 21,
        "gulp": 6,
        "heh": 61,
        "eh": 10,
        "means": 15,
        "anyway": 12,
        "actually": 25,
        "seen": 19,
        "week": 8,
        "applejack": 51,
        "late": 7,
        "athlete": 6,
        "flying": 21,
        "stand": 11,
        "air": 6,
        "faster": 12,
        "amazing": 18,
        "ready": 28,
        "supposed": 23,
        "land": 9,
        "hay": 6,
        "somepony": 25,
        "else": 23,
        "phew": 6,
        "grunt": 9,
        "pie": 55,
        "middle": 7,
        "close": 9,
        "forget": 14,
        "sighs": 57,
        "okay": 85,
        "wanna": 39,
        "home": 21,
        "gilda": 8,
        "half": 7,
        "days": 11,
        "flight": 8,
        "remember": 23,
        "catch": 17,
        "race": 17,
        "win": 27,
        "ahead": 9,
        "beat": 24,
        "hah": 16,
        "try": 21,
        "crazy": 13,
        "laughing": 14,
        "sweet": 13,
        "gotta": 64,
        "care": 11,
        "town": 19,
        "hoof": 14,
        "cake": 7,
        "set": 9,
        "party": 20,
        "guess": 31,
        "cool": 44,
        "sorry": 42,
        "ruined": 7,
        "hard": 26,
        "rest": 11,
        "magic": 8,
        "makes": 9,
        "job": 10,
        "call": 17,
        "sick": 6,
        "ow": 15,
        "fine": 27,
        "equestria": 34,
        "ball": 6,
        "record": 17,
        "six": 10,
        "hundred": 12,
        "start": 12,
        "tell": 50,
        "hooves": 11,
        "takes": 9,
        "bet": 8,
        "nice": 19,
        "slow": 14,
        "check": 8,
        "waiting": 9,
        "told": 16,
        "fault": 9,
        "sigh": 8,
        "idea": 18,
        "bring": 12,
        "hmm": 7,
        "tried": 11,
        "whatever": 18,
        "stop": 33,
        "dragon": 15,
        "move": 17,
        "comes": 12,
        "ground": 10,
        "weird": 11,
        "curse": 9,
        "coming": 18,
        "miss": 16,
        "groans": 23,
        "boring": 13,
        "sound": 12,
        "wow": 19,
        "hold": 14,
        "eating": 8,
        "months": 13,
        "winter": 14,
        "snow": 8,
        "team": 28,
        "um": 18,
        "fast": 25,
        "learn": 16,
        "looks": 27,
        "dark": 10,
        "cloud": 11,
        "happen": 13,
        "listen": 12,
        "class": 7,
        "cutie": 12,
        "mark": 7,
        "baby": 6,
        "lightning": 12,
        "stretch": 6,
        "quickly": 8,
        "whoo": 7,
        "hoo": 6,
        "pegasus": 17,
        "game": 15,
        "throw": 8,
        "lost": 9,
        "hate": 7,
        "top": 10,
        "prove": 6,
        "competition": 15,
        "thanks": 31,
        "believe": 24,
        "won": 7,
        "ride": 10,
        "count": 6,
        "understand": 6,
        "am": 39,
        "wings": 17,
        "easy": 14,
        "excuse": 6,
        "funny": 9,
        "laughs": 19,
        "egghead": 8,
        "read": 13,
        "eye": 6,
        "finish": 17,
        "line": 13,
        "play": 12,
        "gasp": 8,
        "love": 26,
        "fun": 27,
        "cooler": 9,
        "answer": 7,
        "exactly": 17,
        "cheer": 6,
        "breath": 8,
        "cheering": 6,
        "wish": 6,
        "guys": 43,
        "cloudsdale": 24,
        "flyer": 16,
        "kidding": 16,
        "sonic": 11,
        "sleep": 8,
        "entire": 7,
        "day": 37,
        "able": 14,
        "fail": 8,
        "celestia": 10,
        "probably": 19,
        "life": 11,
        "rainboom": 11,
        "starting": 6,
        "bit": 9,
        "nervous": 9,
        "feel": 18,
        "lot": 19,
        "history": 10,
        "doing": 38,
        "doomed": 10,
        "panting": 8,
        "totally": 47,
        "ohmygosh": 11,
        "worry": 16,
        "whispering": 11,
        "asleep": 7,
        "appleloosa": 6,
        "heavy": 6,
        "tree": 7,
        "train": 10,
        "pretty": 44,
        "offense": 9,
        "spike": 23,
        "save": 11,
        "getting": 25,
        "run": 10,
        "trust": 10,
        "ah": 7,
        "apple": 13,
        "talk": 8,
        "brought": 6,
        "explain": 6,
        "trees": 6,
        "looking": 9,
        "story": 21,
        "voiceover": 11,
        "wind": 10,
        "mane": 13,
        "winning": 9,
        "lucky": 9,
        "goes": 6,
        "grunts": 11,
        "surprise": 6,
        "glad": 6,
        "daring": 71,
        "wonderbolt": 25,
        "spitfire": 11,
        "rain": 7,
        "gotcha": 13,
        "storm": 14,
        "leaving": 6,
        "control": 9,
        "nope": 10,
        "discord": 8,
        "night": 12,
        "mad": 7,
        "pet": 18,
        "saying": 10,
        "instead": 9,
        "guts": 7,
        "test": 6,
        "blows": 6,
        "step": 10,
        "possibly": 6,
        "alright": 13,
        "games": 21,
        "qualify": 10,
        "marks": 7,
        "sorta": 6,
        "tortoise": 6,
        "favorite": 9,
        "scary": 7,
        "times": 12,
        "obviously": 10,
        "watch": 12,
        "stuck": 7,
        "happening": 7,
        "trapped": 6,
        "world": 6,
        "whoever": 6,
        "tank": 18,
        "gasps": 34,
        "wrong": 21,
        "hero": 13,
        "dangerous": 7,
        "name": 10,
        "thinking": 9,
        "normal": 6,
        "stay": 12,
        "lunch": 6,
        "muffled": 6,
        "mare": 12,
        "clears": 7,
        "throat": 8,
        "growls": 6,
        "strong": 10,
        "yelps": 8,
        "granny": 6,
        "please": 14,
        "eat": 8,
        "drop": 6,
        "warming": 6,
        "eve": 6,
        "earth": 7,
        "flag": 7,
        "rock": 9,
        "hope": 8,
        "quit": 9,
        "playing": 7,
        "books": 9,
        "cider": 17,
        "joke": 9,
        "reading": 8,
        "blue": 6,
        "wing": 22,
        "noises": 7,
        "excited": 14,
        "finally": 7,
        "hit": 10,
        "found": 7,
        "lose": 7,
        "yawns": 9,
        "statue": 8,
        "ahuizotl": 8,
        "book": 30,
        "bad": 24,
        "steal": 6,
        "knock": 6,
        "las": 6,
        "hushed": 13,
        "dragons": 9,
        "hurt": 10,
        "tonight": 6,
        "water": 9,
        "tornado": 7,
        "power": 9,
        "except": 6,
        "confidence": 8,
        "guard": 6,
        "crystal": 14,
        "castle": 14,
        "empire": 8,
        "feeling": 7,
        "scoffs": 13,
        "scootaloo": 25,
        "spookily": 6,
        "stories": 7,
        "cart": 9,
        "unless": 11,
        "scoot": 6,
        "kinda": 10,
        "definitely": 8,
        "practice": 8,
        "huge": 8,
        "news": 6,
        "plan": 10,
        "dinner": 6,
        "gone": 11,
        "learning": 6,
        "left": 7,
        "helping": 6,
        "hello": 7,
        "adventure": 11,
        "twenty": 7,
        "fan": 13,
        "appreciate": 6,
        "caballeron": 7,
        "coolest": 14,
        "mess": 6,
        "breeze": 8,
        "likes": 6,
        "school": 7,
        "special": 7,
        "cheese": 6,
        "teacher": 6,
        "barely": 7,
        "imitating": 12,
        "gosh": 7,
        "trade": 16,
        "orthros": 6,
        "lamp": 6,
        "chicken": 7,
        "map": 6,
        "griffons": 6,
        "idol": 6,
        "treasure": 6,
        "bunch": 6,
        "rider": 7,
        "worse": 7,
        "percent": 7,
        "club": 11,
        "friendship": 6,
        "parents": 7,
        "yearling": 8,
        "follow": 7,
        "prank": 8,
        "cookies": 12,
        "buckball": 7,
        "dad": 6,
        "magnus": 7,
        "narrating": 12,
        "pies": 14,
        "students": 6
    },
    "fluttershy": {
        "oh": 419,
        "um": 132,
        "stop": 17,
        "please": 40,
        "excuse": 22,
        "mean": 41,
        "tiny": 9,
        "bit": 13,
        "quietly": 15,
        "fluttershy": 27,
        "gasp": 18,
        "baby": 13,
        "dragon": 9,
        "seen": 14,
        "cute": 12,
        "dragons": 7,
        "talk": 14,
        "wonderful": 23,
        "wait": 39,
        "hi": 6,
        "spike": 16,
        "wow": 16,
        "talking": 7,
        "yes": 59,
        "poor": 17,
        "bed": 7,
        "ready": 13,
        "goodness": 45,
        "sorry": 69,
        "girls": 38,
        "bunny": 12,
        "okay": 85,
        "little": 80,
        "hurt": 21,
        "giggles": 12,
        "sometimes": 11,
        "rarity": 46,
        "lovely": 16,
        "looks": 16,
        "cutie": 12,
        "angel": 46,
        "perfect": 14,
        "twilight": 64,
        "else": 17,
        "actually": 21,
        "gala": 8,
        "beautiful": 10,
        "equestria": 20,
        "night": 21,
        "started": 6,
        "hello": 16,
        "hope": 29,
        "mind": 14,
        "doing": 24,
        "late": 14,
        "idea": 14,
        "friend": 27,
        "feel": 33,
        "awful": 16,
        "applejack": 18,
        "helping": 10,
        "gonna": 35,
        "help": 70,
        "thank": 39,
        "job": 8,
        "remember": 13,
        "home": 29,
        "ones": 6,
        "trying": 19,
        "tell": 18,
        "pinkie": 28,
        "pie": 19,
        "party": 19,
        "stuck": 7,
        "throat": 8,
        "water": 7,
        "scary": 13,
        "smoke": 6,
        "time": 61,
        "fire": 6,
        "start": 7,
        "everypony": 38,
        "thinking": 8,
        "maybe": 63,
        "stay": 11,
        "ponyville": 17,
        "guess": 28,
        "scared": 16,
        "eat": 11,
        "pony": 25,
        "afraid": 15,
        "listen": 12,
        "friends": 49,
        "am": 29,
        "creatures": 22,
        "yourself": 14,
        "bad": 14,
        "sleep": 6,
        "animals": 40,
        "care": 16,
        "ground": 8,
        "deep": 13,
        "male": 8,
        "voice": 63,
        "uh": 42,
        "dangerous": 8,
        "coming": 8,
        "sound": 6,
        "normal": 19,
        "la": 27,
        "princess": 24,
        "celestia": 14,
        "believe": 18,
        "found": 20,
        "forest": 13,
        "ugh": 7,
        "tried": 13,
        "food": 9,
        "town": 6,
        "wake": 6,
        "nice": 28,
        "welcome": 10,
        "favorite": 6,
        "animal": 10,
        "look": 42,
        "worried": 10,
        "able": 16,
        "comes": 8,
        "morning": 8,
        "fine": 12,
        "love": 27,
        "wanna": 15,
        "called": 7,
        "true": 11,
        "whatever": 7,
        "getting": 12,
        "fly": 14,
        "muffled": 7,
        "bye": 6,
        "course": 27,
        "control": 6,
        "yay": 11,
        "breath": 6,
        "rainbow": 45,
        "dash": 38,
        "move": 13,
        "close": 8,
        "front": 12,
        "ponies": 32,
        "win": 8,
        "meant": 6,
        "left": 11,
        "special": 15,
        "suppose": 10,
        "fun": 21,
        "sweet": 11,
        "tea": 16,
        "careful": 7,
        "cottage": 8,
        "excited": 14,
        "play": 11,
        "game": 7,
        "quiet": 10,
        "filled": 8,
        "gotten": 9,
        "dark": 8,
        "dream": 6,
        "sing": 11,
        "hard": 14,
        "gasps": 48,
        "gone": 14,
        "looking": 12,
        "means": 10,
        "whispering": 8,
        "hoof": 6,
        "leave": 22,
        "catch": 7,
        "understand": 12,
        "boy": 10,
        "wrong": 13,
        "learned": 10,
        "finish": 9,
        "clears": 6,
        "photo": 6,
        "happy": 21,
        "somepony": 20,
        "fashion": 8,
        "spend": 6,
        "nervous": 7,
        "sighs": 18,
        "promise": 11,
        "model": 6,
        "hate": 12,
        "told": 9,
        "magic": 18,
        "ooh": 21,
        "mad": 9,
        "tree": 10,
        "glad": 14,
        "safe": 8,
        "watch": 6,
        "bring": 7,
        "thanks": 10,
        "taking": 9,
        "met": 6,
        "worry": 15,
        "philomena": 17,
        "cure": 7,
        "dear": 18,
        "sick": 8,
        "try": 28,
        "feeling": 9,
        "likes": 7,
        "rest": 12,
        "own": 12,
        "gotta": 6,
        "fault": 6,
        "pet": 14,
        "banish": 7,
        "happened": 16,
        "anyway": 6,
        "voiceover": 9,
        "moment": 6,
        "heard": 7,
        "hey": 8,
        "house": 10,
        "bear": 8,
        "critters": 6,
        "meet": 8,
        "soon": 9,
        "whoa": 8,
        "none": 7,
        "appreciate": 7,
        "ha": 13,
        "upset": 8,
        "nightmare": 15,
        "flying": 7,
        "plenty": 7,
        "chance": 7,
        "wish": 7,
        "lot": 14,
        "picnic": 6,
        "apple": 8,
        "family": 6,
        "gosh": 7,
        "hmm": 12,
        "bits": 8,
        "matter": 7,
        "exactly": 14,
        "gulps": 6,
        "monster": 6,
        "pretty": 21,
        "day": 13,
        "live": 9,
        "grunts": 7,
        "miss": 8,
        "laughs": 6,
        "wing": 6,
        "sort": 6,
        "crying": 6,
        "terrible": 9,
        "happen": 8,
        "singing": 6,
        "huh": 9,
        "join": 6,
        "pitched": 6,
        "sounds": 13,
        "calling": 6,
        "language": 7,
        "giving": 8,
        "probably": 12,
        "worth": 6,
        "discord": 29,
        "makes": 8,
        "hear": 6,
        "trust": 6,
        "friendship": 10,
        "call": 10,
        "trouble": 6,
        "anypony": 15,
        "castle": 6,
        "lost": 6,
        "vampire": 6,
        "trees": 6,
        "sanctuary": 15,
        "adorable": 6,
        "breezies": 10,
        "funny": 6,
        "music": 8,
        "breeze": 8,
        "seabreeze": 9,
        "bees": 8,
        "serious": 6,
        "book": 10,
        "marks": 7,
        "hushed": 7,
        "spooky": 9,
        "hugger": 6,
        "mask": 11,
        "building": 7,
        "zephyr": 10,
        "gladmane": 6,
        "flam": 6,
        "zecora": 13,
        "swamp": 6,
        "mystical": 7,
        "mage": 6,
        "meadowbrook": 8,
        "shop": 6,
        "snooty": 18,
        "hipster": 9,
        "goth": 8,
        "kirin": 6
    }
}